thegraph_token_api/__init__.py
thegraph_token_api/base.py
thegraph_token_api/client.py
thegraph_token_api/constants.py
thegraph_token_api/evm.py
thegraph_token_api/models.py
thegraph_token_api/price_utils.py
thegraph_token_api/simple.py
thegraph_token_api/svm.py
thegraph_token_api/types.py
thegraph_token_api/unified_price_api.py
divine_thegraph_token_api-0.2.2.dist-info/METADATA
divine_thegraph_token_api-0.2.2.dist-info/WHEEL
divine_thegraph_token_api-0.2.2.dist-info/licenses/LICENSE
divine_thegraph_token_api-0.2.2.dist-info/RECORD
