Metadata-Version: 2.4
Name: divine-thegraph-token-api
Version: 0.2.2
Summary: A Python client for The Graph Token API with elegant EVM/SVM separation and excellent test coverage
Project-URL: Homepage, https://github.com/divinescreener/thegraph-token-api
Project-URL: Issues, https://github.com/divinescreener/thegraph-token-api/issues
Author-email: DIVINE <admin@divine.sh>
License: MIT
License-File: LICENSE
Requires-Python: >=3.13
Requires-Dist: divine-type-enforcer>=0.1.13
Requires-Dist: divine-typed-requests>=0.1.32
Requires-Dist: httpx[http2]>=0.28.1
